LICENSE
MANIFEST.in
NAME
README.md
VERSION
setup.py
pkg/.DS_Store
pkg/90-raspberrystem.rules
pkg/postinstall
raspberrystem.egg-info/PKG-INFO
raspberrystem.egg-info/SOURCES.txt
raspberrystem.egg-info/dependency_links.txt
raspberrystem.egg-info/top_level.txt
rstem/__init__.py
rstem/accel.py
rstem/button.py
rstem/gpio/__init__.py
rstem/led_matrix/__init__.py
rstem/led_matrix/led_driver.c
rstem/led_matrix/font/.DS_Store
rstem/led_matrix/font/large.font
rstem/led_matrix/font/small.font
rstem/led_matrix/font/3x5/.DS_Store
rstem/led_matrix/font/3x5/space.spr
rstem/led_matrix/font/3x5/unknown.spr
rstem/led_matrix/font/3x5/lower/a.spr
rstem/led_matrix/font/3x5/lower/b.spr
rstem/led_matrix/font/3x5/lower/c.spr
rstem/led_matrix/font/3x5/lower/d.spr
rstem/led_matrix/font/3x5/lower/e.spr
rstem/led_matrix/font/3x5/lower/f.spr
rstem/led_matrix/font/3x5/lower/g.spr
rstem/led_matrix/font/3x5/lower/h.spr
rstem/led_matrix/font/3x5/lower/i.spr
rstem/led_matrix/font/3x5/lower/j.spr
rstem/led_matrix/font/3x5/lower/k.spr
rstem/led_matrix/font/3x5/lower/l.spr
rstem/led_matrix/font/3x5/lower/m.spr
rstem/led_matrix/font/3x5/lower/n.spr
rstem/led_matrix/font/3x5/lower/o.spr
rstem/led_matrix/font/3x5/lower/p.spr
rstem/led_matrix/font/3x5/lower/q.spr
rstem/led_matrix/font/3x5/lower/r.spr
rstem/led_matrix/font/3x5/lower/s.spr
rstem/led_matrix/font/3x5/lower/t.spr
rstem/led_matrix/font/3x5/lower/u.spr
rstem/led_matrix/font/3x5/lower/v.spr
rstem/led_matrix/font/3x5/lower/w.spr
rstem/led_matrix/font/3x5/lower/x.spr
rstem/led_matrix/font/3x5/lower/y.spr
rstem/led_matrix/font/3x5/lower/z.spr
rstem/led_matrix/font/3x5/misc/33.spr
rstem/led_matrix/font/3x5/misc/35.spr
rstem/led_matrix/font/3x5/misc/37.spr
rstem/led_matrix/font/3x5/misc/40.spr
rstem/led_matrix/font/3x5/misc/41.spr
rstem/led_matrix/font/3x5/misc/43.spr
rstem/led_matrix/font/3x5/misc/44.spr
rstem/led_matrix/font/3x5/misc/45.spr
rstem/led_matrix/font/3x5/misc/46.spr
rstem/led_matrix/font/3x5/misc/47.spr
rstem/led_matrix/font/3x5/misc/58.spr
rstem/led_matrix/font/3x5/misc/61.spr
rstem/led_matrix/font/3x5/misc/63.spr
rstem/led_matrix/font/3x5/misc/64.spr
