Metadata-Version: 1.1
Name: raspberrystem
Version: 1.0.0
Summary: RaspberrySTEM API
Home-page: http://www.raspberrystem.com
Author: Brian Silverman
Author-email: bri@raspberrystem.com
License: Apache License 2.0
Keywords: raspberrystem,raspberrypi,stem
Platform: UNKNOWN
Classifier: Development Status :: 4 - Beta
Classifier: Topic :: Education
Classifier: License :: OSI Approved :: Apache Software License
Classifier: Programming Language :: Python :: 3.2
Classifier: Programming Language :: Python :: 3.3
